README.rst
flask_envconfig.py
setup.py
Flask_EnvConfig.egg-info/PKG-INFO
Flask_EnvConfig.egg-info/SOURCES.txt
Flask_EnvConfig.egg-info/dependency_links.txt
Flask_EnvConfig.egg-info/not-zip-safe
Flask_EnvConfig.egg-info/requires.txt
Flask_EnvConfig.egg-info/top_level.txt