Metadata-Version: 1.1
Name: Flask-EnvConfig
Version: 0.1.0
Summary: Configure Flask from environment variables.
Home-page: https://bitbucket.org/romabysen/flask-envconfig/
Author: Lars Hansson
Author-email: romabysen@gmail.com
License: BSD
Platform: any
Classifier: Environment :: Web Environment
Classifier: Intended Audience :: Developers
Classifier: License :: OSI Approved :: BSD License
Classifier: Operating System :: OS Independent
Classifier: Programming Language :: Python
Classifier: Topic :: Internet :: WWW/HTTP :: Dynamic Content
Classifier: Topic :: Software Development :: Libraries :: Python Modules
